mesos_cook/__init__.py
mesos_cook/__version__.py
mesos_cook/cli.py
mesos_cook/client.py
mesos_cook/logs.py
mesos_cook/model.py
mesos_cook/schemas.py
mesos_cook-0.3.4.dist-info/DESCRIPTION.rst
mesos_cook-0.3.4.dist-info/METADATA
mesos_cook-0.3.4.dist-info/RECORD
mesos_cook-0.3.4.dist-info/WHEEL
mesos_cook-0.3.4.dist-info/entry_points.txt
mesos_cook-0.3.4.dist-info/metadata.json
mesos_cook-0.3.4.dist-info/top_level.txt
mesos_cook-0.3.4.dist-info/zip-safe
