Metadata-Version: 1.0
Name: mesos_cook
Version: 0.3.4
Summary: Python client for Two Sigma's Cook scheduler
Home-page: https://github.com/roguePanda/mesos_cook
Author: Ben Navetta
Author-email: benjamin_navetta@brown.edu
License: MIT
Platform: UNKNOWN
